envoy/gpg/sign/__init__.py
envoy/gpg/sign/bin.py
envoy/gpg/sign/cmd.py
envoy/gpg/sign/deb.py
envoy/gpg/sign/exceptions.py
envoy/gpg/sign/py.typed
envoy/gpg/sign/rpm.py
envoy/gpg/sign/runner.py
envoy/gpg/sign/util.py
envoy.gpg.sign-0.2.0.dist-info/METADATA
envoy.gpg.sign-0.2.0.dist-info/WHEEL
envoy.gpg.sign-0.2.0.dist-info/entry_points.txt
envoy.gpg.sign-0.2.0.dist-info/namespace_packages.txt
envoy.gpg.sign-0.2.0.dist-info/top_level.txt
envoy.gpg.sign-0.2.0.dist-info/RECORD
