Metadata-Version: 2.1
Name: envoy.gpg.sign
Version: 0.2.0
Summary: "GPG signing util used in Envoy proxy's CI"
Home-page: https://github.com/envoyproxy/pytooling/tree/main/envoy.gpg.sign
Author: Ryan Northey
Author-email: ryan@synca.io
Maintainer: Ryan Northey
Maintainer-email: ryan@synca.io
License: Apache Software License 2.0
Requires-Python: >=3.10.0
Requires-Dist: aio.run.runner (>=0.3.3)
Requires-Dist: envoy.base.utils (>=0.4.7)
Requires-Dist: envoy.gpg.identity (>=0.1.1)
